sqlfluff_templater_dataform_full/__init__.py
sqlfluff_templater_dataform_full/templater.py
sqlfluff_templater_dataform_full-0.1.3.dist-info/licenses/LICENSE
sqlfluff_templater_dataform_full-0.1.3.dist-info/METADATA
sqlfluff_templater_dataform_full-0.1.3.dist-info/WHEEL
sqlfluff_templater_dataform_full-0.1.3.dist-info/entry_points.txt
sqlfluff_templater_dataform_full-0.1.3.dist-info/top_level.txt
sqlfluff_templater_dataform_full-0.1.3.dist-info/RECORD
