Metadata-Version: 2.4
Name: sqlfluff-templater-dataform-full
Version: 0.1.3
Summary: Lint your Dataform project SQL
Author-email: Taras Kopets <tkopets@gmail.com>
License-Expression: MIT
Keywords: sqlfluff,sql,linter,formatter,bigquery,dataform,templater
Classifier: Environment :: Console
Classifier: Development Status :: 3 - Alpha
Classifier: Intended Audience :: Developers
Classifier: Operating System :: Unix
Classifier: Operating System :: POSIX
Classifier: Operating System :: MacOS
Classifier: Operating System :: Microsoft :: Windows
Classifier: Topic :: Utilities
Classifier: Topic :: Software Development :: Quality Assurance
Requires-Python: >=3.9
License-File: LICENSE
Requires-Dist: sqlfluff>=3.4.2
Requires-Dist: typing-extensions>=4.0.0
Provides-Extra: dev
Requires-Dist: pytest; extra == "dev"
Requires-Dist: ruff; extra == "dev"
Requires-Dist: mypy; extra == "dev"
Requires-Dist: poethepoet; extra == "dev"
Requires-Dist: build; extra == "dev"
Dynamic: license-file
